analyst/__init__.py
analyst/bindingmanager.py
analyst/colors.py
analyst/cursors.py
analyst/datanormalizer.py
analyst/debugtools.py
analyst/glrenderer.py
analyst/icons.py
analyst/interactionmanager.py
analyst/manager.py
analyst/paintmanager.py
analyst/pyplot.py
analyst/scene.py
analyst/tools.py
analyst/useractions.py
analyst/widget.py
analyst/managers/__init__.py
analyst/managers/default_manager.py
analyst/managers/mesh_manager.py
analyst/managers/plot_manager.py
analyst/processors/__init__.py
analyst/processors/default_processor.py
analyst/processors/grid_processor.py
analyst/processors/mesh_processor.py
analyst/processors/navigation_processor.py
analyst/processors/processor.py
analyst/test/__init__.py
analyst/test/test.py
analyst/visuals/__init__.py
analyst/visuals/bar_visual.py
analyst/visuals/framebuffer_visual.py
analyst/visuals/graph_visual.py
analyst/visuals/grid_visual.py
analyst/visuals/mesh_visual.py
analyst/visuals/plot_visual.py
analyst/visuals/rectangles_visual.py
analyst/visuals/sprite_visual.py
analyst/visuals/surface_visual.py
analyst/visuals/text_visual.py
analyst/visuals/texture_visual.py
analyst/visuals/visual.py
analyst/visuals/fontmaps/__init__.py
analyst/visuals/fontmaps/tools.py
D_Analyst-1.0.6.dist-info/LICENSE.txt
D_Analyst-1.0.6.dist-info/METADATA
D_Analyst-1.0.6.dist-info/WHEEL
D_Analyst-1.0.6.dist-info/top_level.txt
D_Analyst-1.0.6.dist-info/RECORD
