Metadata-Version: 2.1
Name: D-Analyst
Version: 1.0.6
Summary: An interactive data visualization library
Home-page: https://github.com/Diachronic-Technologies/D-Analyst
Author: Agbakosi Adeoluwa(180 Memes), Diachronic Technologies
Author-email: adeoluwaagbakosi@gmail.com
License: UNKNOWN
Project-URL: Bug Tracker, https://github.com/Diachronic-Technologies/D-Analyst/issues
Platform: UNKNOWN
Classifier: Programming Language :: Python :: 3
Classifier: License :: OSI Approved :: MIT License
Classifier: Operating System :: OS Independent
Requires-Python: >=3.6
License-File: LICENSE.txt
Requires-Dist: QPlug
